[
  {
    "id": 1,
    "name": "John Doe",
    "picture": "https://reqres.in/img/faces/1-image.jpg",
    "email": "john@example.com",
    "days_since_contact": 12,
    "status": "on track",
    "tags": ["college", "close friend"],
    "bio": "Met in university. Loves hiking together.",
    "goal": 14,
    "next_due_date": "2026-06-02"
  },
  {
    "id": 2,
    "name": "Alex Mercer",
    "picture": "https://reqres.in/img/faces/2-image.jpg",
    "email": "alex@example.com",
    "days_since_contact": 25,
    "status": "overdue",
    "tags": ["school", "gaming"],
    "bio": "Childhood friend. We play multiplayer games on weekends.",
    "goal": 15,
    "next_due_date": "2026-05-13"
  },
  {
    "id": 3,
    "name": "Sarah Jenkins",
    "picture": "https://reqres.in/img/faces/3-image.jpg",
    "email": "sarah@example.com",
    "days_since_contact": 5,
    "status": "on track",
    "tags": ["work", "mentor"],
    "bio": "Former colleague who guides me through tech stack decisions.",
    "goal": 30,
    "next_due_date": "2026-06-17"
  },
  {
    "id": 4,
    "name": "David Kim",
    "picture": "https://reqres.in/img/faces/4-image.jpg",
    "email": "david.k@example.com",
    "days_since_contact": 45,
    "status": "overdue",
    "tags": ["gym", "fitness"],
    "bio": "Gym partner. Need to catch up on our workout routine.",
    "goal": 30,
    "next_due_date": "2026-05-08"
  },
  {
    "id": 5,
    "name": "Emily Watson",
    "picture": "https://reqres.in/img/faces/5-image.jpg",
    "email": "emily@example.com",
    "days_since_contact": 2,
    "status": "on track",
    "tags": ["neighborhood", "close friend"],
    "bio": "Next-door neighbor. Always down for coffee and gossip.",
    "goal": 7,
    "next_due_date": "2026-05-28"
  },
  {
    "id": 6,
    "name": "Michael Chang",
    "picture": "https://reqres.in/img/faces/6-image.jpg",
    "email": "michael.c@example.com",
    "days_since_contact": 60,
    "status": "overdue",
    "tags": ["college", "coding"],
    "bio": "Hackathon partner from college. Lives in another city now.",
    "goal": 45,
    "next_due_date": "2026-04-08"
  },
  {
    "id": 7,
    "name": "Jessica Taylor",
    "picture": "https://reqres.in/img/faces/7-image.jpg",
    "email": "jess@example.com",
    "days_since_contact": 1,
    "status": "on track",
    "tags": ["best friend", "travel"],
    "bio": "Best friend since high school. We talk almost every day.",
    "goal": 3,
    "next_due_date": "2026-05-25"
  },
  {
    "id": 8,
    "name": "Ryan Reynolds",
    "picture": "https://reqres.in/img/faces/8-image.jpg",
    "email": "ryan.r@example.com",
    "days_since_contact": 18,
    "status": "overdue",
    "tags": ["photography", "club"],
    "bio": "Met at the local photography club. Great at portrait tips.",
    "goal": 14,
    "next_due_date": "2026-05-19"
  },
  {
    "id": 9,
    "name": "Sophia Martinez",
    "picture": "https://reqres.in/img/faces/9-image.jpg",
    "email": "sophia@example.com",
    "days_since_contact": 10,
    "status": "on track",
    "tags": ["books", "community"],
    "bio": "Co-founder of our monthly book reading club.",
    "goal": 20,
    "next_due_date": "2026-06-02"
  },
  {
    "id": 10,
    "name": "James Wilson",
    "picture": "https://reqres.in/img/faces/10-image.jpg",
    "email": "james.w@example.com",
    "days_since_contact": 35,
    "status": "overdue",
    "tags": ["music", "band"],
    "bio": "Guitarist friend. We used to jam together in college.",
    "goal": 30,
    "next_due_date": "2026-05-18"
  },
  {
    "id": 11,
    "name": "Lily Evans",
    "picture": "https://reqres.in/img/faces/11-image.jpg",
    "email": "lily.e@example.com",
    "days_since_contact": 4,
    "status": "on track",
    "tags": ["college", "project"],
    "bio": "CSE classmate. Working together on web app projects.",
    "goal": 7,
    "next_due_date": "2026-05-26"
  },
  {
    "id": 12,
    "name": "Daniel Brooks",
    "picture": "https://reqres.in/img/faces/12-image.jpg",
    "email": "daniel@example.com",
    "days_since_contact": 90,
    "status": "overdue",
    "tags": ["childhood"],
    "bio": "Old town friend. Haven't heard from him in a while.",
    "goal": 60,
    "next_due_date": "2026-04-23"
  }
]